crowdai/__init__.py
crowdai/config.py
crowdai/challenges/__init__.py
crowdai/challenges/ai_generated_music_challenge.py
crowdai/challenges/base_challenge.py
crowdai/challenges/criteo_ad_placement_challenge_nips_2017.py
crowdai/challenges/crowdai_errors.py
crowdai/challenges/crowdai_mapping_challenge.py
crowdai/challenges/events.py
crowdai/challenges/gecco_optimization_challenge_2017.py
crowdai/challenges/ieee_investment_ranking_challenge.py
crowdai/challenges/job_states.py
crowdai/challenges/kit_energy_challenge.py
crowdai/challenges/learning_2_run_challenge_nips_2017.py
crowdai/challenges/logging_helpers.py
crowdai/challenges/opensnp_challenge_2017.py
crowdai/challenges/response_types.py
crowdai/challenges/upload_helpers.py
crowdai/challenges/www_musical_genre_challenge.py
crowdai-1.0.19.dist-info/DESCRIPTION.rst
crowdai-1.0.19.dist-info/METADATA
crowdai-1.0.19.dist-info/RECORD
crowdai-1.0.19.dist-info/WHEEL
crowdai-1.0.19.dist-info/metadata.json
crowdai-1.0.19.dist-info/top_level.txt
