Metadata-Version: 2.0
Name: crowdai
Version: 1.0.19
Summary: Python client to interact with CrowdAI Grading Server.
Home-page: https://github.com/spMohanty/crowdai-client-py
Author: S.P. Mohanty
Author-email: sharada.mohanty@epfl.ch
License: GPLv3
Download-URL: https://github.com/spMohanty/crowdai-client-py
Platform: UNKNOWN
Requires-Dist: appdirs (<1.5,>=1.4)
Requires-Dist: click (==6.7)
Requires-Dist: enum-compat (==0.0.2)
Requires-Dist: enum34 (<1.2,>=1.1.6)
Requires-Dist: Flask (<0.13,>=0.12.1)
Requires-Dist: itsdangerous (==0.24)
Requires-Dist: Jinja2 (==2.9.6)
Requires-Dist: MarkupSafe (==1.0)
Requires-Dist: packaging (==16.8)
Requires-Dist: pyparsing (<2.3,>=2.2)
Requires-Dist: requests (<2.15,>=2.14)
Requires-Dist: six (<1.11,>=1.10)
Requires-Dist: socketIO-client-2 (<0.8,>=0.7)
Requires-Dist: termcolor (<1.2,>=1.1)
Requires-Dist: tqdm (<4.12,>=4.11)
Requires-Dist: websocket-client (<0.41,>=0.40)
Requires-Dist: Werkzeug (<0.13,>=0.12.1)
